Workbook

Sheet 📊 Dashboard
A1: 🗄 SQL Practice — 54 Queries on the sql_practice Database
A2: Topic | B2: Total | C2: Easy | D2: Medium | E2: Hard | F2: ✅ Done | G2: % Done
A3: 1. SELECT basics | B3: =COUNTIF('🧩 Practice Queries'!$B$3:$B$56,A3) -> 6 | C3: =COUNTIFS('🧩 Practice Queries'!$B$3:$B$56,A3,'🧩 Practice Queries'!$C$3:$C$56,"Easy") -> 4 | D3: =COUNTIFS('🧩 Practice Queries'!$B$3:$B$56,A3,'🧩 Practice Queries'!$C$3:$C$56,"Medium") -> 2 | E3: =COUNTIFS('🧩 Practice Queries'!$B$3:$B$56,A3,'🧩 Practice Queries'!$C$3:$C$56,"Hard") -> 0 | F3: =COUNTIFS('🧩 Practice Queries'!$B$3:$B$56,A3,'🧩 Practice Queries'!$F$3:$F$56,"✅ Done") -> 0 | G3: =IF(B3=0,0,F3/B3) -> 0
A4: 2. Filtering | B4: =COUNTIF('🧩 Practice Queries'!$B$3:$B$56,A4) -> 6 | C4: =COUNTIFS('🧩 Practice Queries'!$B$3:$B$56,A4,'🧩 Practice Queries'!$C$3:$C$56,"Easy") -> 3 | D4: =COUNTIFS('🧩 Practice Queries'!$B$3:$B$56,A4,'🧩 Practice Queries'!$C$3:$C$56,"Medium") -> 3 | E4: =COUNTIFS('🧩 Practice Queries'!$B$3:$B$56,A4,'🧩 Practice Queries'!$C$3:$C$56,"Hard") -> 0 | F4: =COUNTIFS('🧩 Practice Queries'!$B$3:$B$56,A4,'🧩 Practice Queries'!$F$3:$F$56,"✅ Done") -> 0 | G4: =IF(B4=0,0,F4/B4) -> 0
A5: 3. Aggregation | B5: =COUNTIF('🧩 Practice Queries'!$B$3:$B$56,A5) -> 6 | C5: =COUNTIFS('🧩 Practice Queries'!$B$3:$B$56,A5,'🧩 Practice Queries'!$C$3:$C$56,"Easy") -> 2 | D5: =COUNTIFS('🧩 Practice Queries'!$B$3:$B$56,A5,'🧩 Practice Queries'!$C$3:$C$56,"Medium") -> 3 | E5: =COUNTIFS('🧩 Practice Queries'!$B$3:$B$56,A5,'🧩 Practice Queries'!$C$3:$C$56,"Hard") -> 1 | F5: =COUNTIFS('🧩 Practice Queries'!$B$3:$B$56,A5,'🧩 Practice Queries'!$F$3:$F$56,"✅ Done") -> 0 | G5: =IF(B5=0,0,F5/B5) -> 0
A6: 4. Joins | B6: =COUNTIF('🧩 Practice Queries'!$B$3:$B$56,A6) -> 6 | C6: =COUNTIFS('🧩 Practice Queries'!$B$3:$B$56,A6,'🧩 Practice Queries'!$C$3:$C$56,"Easy") -> 1 | D6: =COUNTIFS('🧩 Practice Queries'!$B$3:$B$56,A6,'🧩 Practice Queries'!$C$3:$C$56,"Medium") -> 3 | E6: =COUNTIFS('🧩 Practice Queries'!$B$3:$B$56,A6,'🧩 Practice Queries'!$C$3:$C$56,"Hard") -> 2 | F6: =COUNTIFS('🧩 Practice Queries'!$B$3:$B$56,A6,'🧩 Practice Queries'!$F$3:$F$56,"✅ Done") -> 0 | G6: =IF(B6=0,0,F6/B6) -> 0
A7: 5. Subqueries | B7: =COUNTIF('🧩 Practice Queries'!$B$3:$B$56,A7) -> 6 | C7: =COUNTIFS('🧩 Practice Queries'!$B$3:$B$56,A7,'🧩 Practice Queries'!$C$3:$C$56,"Easy") -> 0 | D7: =COUNTIFS('🧩 Practice Queries'!$B$3:$B$56,A7,'🧩 Practice Queries'!$C$3:$C$56,"Medium") -> 3 | E7: =COUNTIFS('🧩 Practice Queries'!$B$3:$B$56,A7,'🧩 Practice Queries'!$C$3:$C$56,"Hard") -> 3 | F7: =COUNTIFS('🧩 Practice Queries'!$B$3:$B$56,A7,'🧩 Practice Queries'!$F$3:$F$56,"✅ Done") -> 0 | G7: =IF(B7=0,0,F7/B7) -> 0
A8: 6. CASE & cond. agg | B8: =COUNTIF('🧩 Practice Queries'!$B$3:$B$56,A8) -> 6 | C8: =COUNTIFS('🧩 Practice Queries'!$B$3:$B$56,A8,'🧩 Practice Queries'!$C$3:$C$56,"Easy") -> 1 | D8: =COUNTIFS('🧩 Practice Queries'!$B$3:$B$56,A8,'🧩 Practice Queries'!$C$3:$C$56,"Medium") -> 4 | E8: =COUNTIFS('🧩 Practice Queries'!$B$3:$B$56,A8,'🧩 Practice Queries'!$C$3:$C$56,"Hard") -> 1 | F8: =COUNTIFS('🧩 Practice Queries'!$B$3:$B$56,A8,'🧩 Practice Queries'!$F$3:$F$56,"✅ Done") -> 0 | G8: =IF(B8=0,0,F8/B8) -> 0
A9: 7. Window funcs | B9: =COUNTIF('🧩 Practice Queries'!$B$3:$B$56,A9) -> 6 | C9: =COUNTIFS('🧩 Practice Queries'!$B$3:$B$56,A9,'🧩 Practice Queries'!$C$3:$C$56,"Easy") -> 0 | D9: =COUNTIFS('🧩 Practice Queries'!$B$3:$B$56,A9,'🧩 Practice Queries'!$C$3:$C$56,"Medium") -> 3 | E9: =COUNTIFS('🧩 Practice Queries'!$B$3:$B$56,A9,'🧩 Practice Queries'!$C$3:$C$56,"Hard") -> 3 | F9: =COUNTIFS('🧩 Practice Queries'!$B$3:$B$56,A9,'🧩 Practice Queries'!$F$3:$F$56,"✅ Done") -> 0 | G9: =IF(B9=0,0,F9/B9) -> 0
A10: 8. CTEs & recursion | B10: =COUNTIF('🧩 Practice Queries'!$B$3:$B$56,A10) -> 6 | C10: =COUNTIFS('🧩 Practice Queries'!$B$3:$B$56,A10,'🧩 Practice Queries'!$C$3:$C$56,"Easy") -> 0 | D10: =COUNTIFS('🧩 Practice Queries'!$B$3:$B$56,A10,'🧩 Practice Queries'!$C$3:$C$56,"Medium") -> 3 | E10: =COUNTIFS('🧩 Practice Queries'!$B$3:$B$56,A10,'🧩 Practice Queries'!$C$3:$C$56,"Hard") -> 3 | F10: =COUNTIFS('🧩 Practice Queries'!$B$3:$B$56,A10,'🧩 Practice Queries'!$F$3:$F$56,"✅ Done") -> 0 | G10: =IF(B10=0,0,F10/B10) -> 0
A11: 9. Dates & advanced | B11: =COUNTIF('🧩 Practice Queries'!$B$3:$B$56,A11) -> 6 | C11: =COUNTIFS('🧩 Practice Queries'!$B$3:$B$56,A11,'🧩 Practice Queries'!$C$3:$C$56,"Easy") -> 0 | D11: =COUNTIFS('🧩 Practice Queries'!$B$3:$B$56,A11,'🧩 Practice Queries'!$C$3:$C$56,"Medium") -> 2 | E11: =COUNTIFS('🧩 Practice Queries'!$B$3:$B$56,A11,'🧩 Practice Queries'!$C$3:$C$56,"Hard") -> 4 | F11: =COUNTIFS('🧩 Practice Queries'!$B$3:$B$56,A11,'🧩 Practice Queries'!$F$3:$F$56,"✅ Done") -> 0 | G11: =IF(B11=0,0,F11/B11) -> 0
A12: TOTAL | B12: =SUM(B3:B11) -> 54 | C12: =SUM(C3:C11) -> 11 | D12: =SUM(D3:D11) -> 26 | E12: =SUM(E3:E11) -> 17 | F12: =SUM(F3:F11) -> 0 | G12: =IF(B12=0,0,F12/B12) -> 0
A14: Setup: load schema_and_seed_mysql.sql into MySQL (DBeaver: open file → Execute SQL Script). Write queries in DBeaver, track Status here. Solutions are HIDDEN to keep you honest — right-click any sheet tab → Unhide → 🔑 Solutions when you truly need them. Use 🤖 Ask AI to generate a review/teaching prompt for every query you write.

Sheet 🗄 Schema
A1: Database Schema — sql_practice (MySQL 8)
A2: Table | B2: Column | C2: Type | D2: Key / Notes
A3: employees | B3: employee_id | C3: INT | D3: PK
B4: name | C4: VARCHAR(100) | D4: NOT NULL
B5: title | C5: VARCHAR(100)
B6: department | C6: VARCHAR(50) | D6: Executive / Engineering / Sales
B7: manager_id | C7: INT | D7: FK → employees.employee_id (self-join!); NULL for the CEO
B8: hire_date | C8: DATE
B9: salary | C9: INT
A10: customers | B10: customer_id | C10: INT | D10: PK
B11: name | C11: VARCHAR(100) | D11: NOT NULL
B12: email | C12: VARCHAR(150)
B13: city | C13: VARCHAR(50) | D13: Uneven distribution — some cities have >2 customers
B14: country | C14: VARCHAR(50) | D14: India / UK / USA / Germany
B15: segment | C15: VARCHAR(20) | D15: Consumer / SME / Enterprise
B16: signup_date | C16: DATE | D16: 2022–2024
A17: products | B17: product_id | C17: INT | D17: PK
B18: name | C18: VARCHAR(100) | D18: NOT NULL
B19: category | C19: VARCHAR(50) | D19: Electronics / Accessories / Home / Books / Software
B20: price | C20: DECIMAL(10,2)
B21: cost | C21: DECIMAL(10,2) | D21: NULL for one product (IS NULL practice)
A22: orders | B22: order_id | C22: INT | D22: PK
B23: customer_id | C23: INT | D23: FK → customers; two customers have NO orders
B24: order_date | C24: DATE | D24: Jan 2023 – Oct 2024
B25: status | C25: VARCHAR(20) | D25: PLACED / SHIPPED / DELIVERED / CANCELLED / RETURNED
B26: channel | C26: VARCHAR(10) | D26: WEB / MOBILE / STORE
A27: order_items | B27: order_item_id | C27: INT | D27: PK
B28: order_id | C28: INT | D28: FK → orders
B29: product_id | C29: INT | D29: FK → products; one product is never ordered
B30: quantity | C30: INT | D30: 1–3
B31: unit_price | C31: DECIMAL(10,2) | D31: Some lines carry a 10% discount vs list price
A32: payments | B32: payment_id | C32: INT | D32: PK
B33: order_id | C33: INT | D33: FK → orders; CANCELLED orders have no payment
B34: amount | C34: DECIMAL(12,2) | D34: Equals the order's item total
B35: payment_date | C35: DATE
B36: method | C36: VARCHAR(20) | D36: CARD / UPI / NETBANKING / WALLET / COD
B37: status | C37: VARCHAR(20) | D37: SUCCESS / FAILED / REFUNDED — some orders have 2 payment rows
A39: Row counts: employees 12 · customers 20 · products 15 · orders 50 · order_items 101 · payments 52
A40: Planted edge cases: customers 19 & 20 never ordered · product 15 never sold · orders 5 & 23 unpaid · product 13 has NULL cost · customer 13 ordered only in 2023 · orders 8 & 17 have a FAILED then SUCCESS payment · 2 orders RETURNED with a REFUNDED payment.

Sheet 🧩 Practice Queries
A1: Practice Queries — write your SQL in DBeaver, track status here
A2: # | B2: Topic | C2: Diff | D2: Question | E2: 💡 Hint (hover) | F2: Status | G2: Attempts | H2: My Notes
A3: 1 | B3: 1. SELECT basics | C3: Easy | D3: List every product with its name, category and price, most expensive first. | E3: 👁 hover | F3: ⬜ Todo
A4: 2 | B4: 1. SELECT basics | C4: Easy | D4: Show the distinct cities customers live in, alphabetically. | E4: 👁 hover | F4: ⬜ Todo
A5: 3 | B5: 1. SELECT basics | C5: Easy | D5: Show the name and city of every Enterprise-segment customer. | E5: 👁 hover | F5: ⬜ Todo
A6: 4 | B6: 1. SELECT basics | C6: Easy | D6: Find the 5 most expensive products (name, price). | E6: 👁 hover | F6: ⬜ Todo
A7: 5 | B7: 1. SELECT basics | C7: Medium | D7: List products priced between 1000 and 5000, cheapest first. | E7: 👁 hover | F7: ⬜ Todo
A8: 6 | B8: 1. SELECT basics | C8: Medium | D8: For Electronics, show name and a 20%-off price as discounted_price. | E8: 👁 hover | F8: ⬜ Todo
A9: 7 | B9: 2. Filtering | C9: Easy | D9: Customers who signed up during 2023 (name, signup_date). | E9: 👁 hover | F9: ⬜ Todo
A10: 8 | B10: 2. Filtering | C10: Easy | D10: Orders that were CANCELLED or RETURNED. | E10: 👁 hover | F10: ⬜ Todo
A11: 9 | B11: 2. Filtering | C11: Easy | D11: Customers whose name starts with the letter A. | E11: 👁 hover | F11: ⬜ Todo
A12: 10 | B12: 2. Filtering | C12: Medium | D12: Products that have no cost recorded. | E12: 👁 hover | F12: ⬜ Todo
A13: 11 | B13: 2. Filtering | C13: Medium | D13: WEB-channel orders placed in Q1 2024. | E13: 👁 hover | F13: ⬜ Todo
A14: 12 | B14: 2. Filtering | C14: Medium | D14: All payments that did not succeed. | E14: 👁 hover | F14: ⬜ Todo
... A56: 54 | B56: 9. Dates & advanced | C56: Hard | D56: New customers acquired per signup month (signup_month, new_customers). | E56: 👁 hover | F56: ⬜ Todo

Sheet 🤖 Ask AI
A1: 🤖 SQL Review Prompt Generator — for Copilot / ChatGPT / Gemini / Claude | L1: engine | M1: =IFERROR(MATCH($C$3,'⚙ data'!$A$2:$A$55,0),0) -> 1
M2: =IF($M$1=0,"",INDEX('⚙ data'!$D$2:$D$55,$M$1)) -> List every product with its name, category and price, most expensive first.
B3: 1) Query # (1–54) | C3: 1 | M3: =IF($M$1=0,"",INDEX('⚙ data'!$B$2:$B$55,$M$1)) -> 1. SELECT basics
B4: 2) Mode | C4: Teach step-by-step | M4: =IF($M$1=0,"",INDEX('⚙ data'!$C$2:$C$55,$M$1)) -> Easy
B5: 3) My SQL (paste from DBeaver — double-click the cell first) | M5: =IF($M$1=0,"",INDEX('⚙ data'!$E$2:$E$55,$M$1)) -> 15 rows sorted by price.
B7: Resolved → Question | C7: =IF($M$1=0,"⚠ enter a valid Query # (1–54)",$M$2) -> List every product with its name, category and price, most expensive first.
B8: Topic · Diff · Expected | C8: =IF($M$1=0,"",$M$3&" · "&$M$4&" · expected: "&$M$5) -> 1. SELECT basics · Easy · expected: 15 rows sorted by price.
B10: ✅ Generated prompt | C10: (click the cell below → Ctrl+C → paste into Copilot/your AI chat)
B11: ="You are a MySQL 8 tutor reviewing a practice query. I am a senior Java developer strengthening my SQL for product-company interviews. My weak areas are JOIN, GROUP BY and HAVING — whenever any of these appear, slow down and explain them explicitly rather than assuming I follow."&CHAR(10)&""&CHAR(10)&"Schema (MySQL 8, database sql_practice): customers(customer_id PK, name, email, city, country, segment Consumer/SME/Enterprise, signup_date) | orders(order_id PK, customer_id FK, order_date, status PLACED/SHIPPED/DELIVERED/CANCELLED/RETURNED, channel WEB/MOBILE/STORE) | order_items(order_item_id PK, order_id FK, product_id FK, quantity, unit_price) | products(product_id PK, name, category, price, cost — cost is NULL for one product) | payments(payment_id PK, order_id FK, amount, payment_date, method, status SUCCESS/FAILED/REFUNDED) | employees(employee_id PK, name, title, department, manager_id self-FK NULL for CEO, hire_date, salary)"&CHAR(10)&"Data quirks to reason about: customers 19 & 20 never ordered; product 15 never sold; orders 5 & 23 are CANCELLED with no payment row; some orders have a FAILED payment followed by a SUCCESS; RETURNED orders also carry a REFUNDED payment, so filtering payments on status matters."&CHAR(10)&""&CHAR(10)&"Question #"&$C$3&" ("&$M$3&", "&$M$4&"): "&$M$2&CHAR(10)&"Expected result shape: "&$M$5&CHAR(10)&""&CHAR(10)&"My SQL:"&CHAR(10)&"```sql"&CHAR(10)&IF(TRIM($C$5)="","<PASTE YOUR SQL HERE>",$C$5)&CHAR(10)&"```"&CHAR(10)&""&CHAR(10)&IF($C$4="Hint only — I am stuck","Task: I have NOT solved this yet. Do NOT show me the full query. Give: (a) which tables I need and why, (b) the first clause I should write, (c) one conceptual hint about the trickiest part. Stop there — let me try.",IF($C$4="Teach step-by-step","Task: 1. Say if my query answers the question correctly (check joins, filters, grouping). 2. TEACH the logical execution order for THIS query — FROM, JOIN (show what the joined rows look like), WHERE, GROUP BY (what each group contains), HAVING (which groups survive), SELECT, ORDER BY — with a tiny worked example of the intermediate result at each stage. 3. Point out exactly where my mental model went wrong if it did. 4. Only then show the corrected/idiomatic query. 5. Give me ONE rule of thumb to remember for next time.","Task: 1. Is my query correct for the question? Check join conditions, row multiplication, WHERE vs HAVING placement, and NULL handling. 2. State what my query actually returns if it differs from what was asked. 3. Show the corrected or more idiomatic MySQL 8 version AFTER explaining the issue. 4. Mention any index or performance note an interviewer would expect. 5. Verdict: correct / minor fix / wrong approach."))&CHAR(10)&""&CHAR(10)&"Be direct — name real mistakes plainly. Do not pad with praise." -> You are a MySQL 8 tutor reviewing a practice query. I am a senior Java developer strengthening my SQL for product-company interviews. My weak areas are JOIN, GROUP BY and HAVING — whenever any of these appear, slow down and explain them explicitly rather than assuming I follow. Schema (MySQL 8, database sql_practice): customers(customer_id PK, name, email, city, country, segment Consumer/SME/Enterprise, signup_date) | orders(order_id PK, customer_id FK, order_date, status PLACED/SHIPPED/DELIVERED/CANCELLED/RETURNED, channel WEB/MOBILE/STORE) | order_items(order_item_id PK, order_id FK, product_id FK, quantity, unit_price) | products(product_id PK, name, category, price, cost — cost is NULL for one product) | payments(payment_id PK, order_id FK, amount, payment_date, method, status SUCCESS/FAILED/REFUNDED) | employees(employee_id PK, name, title, department, manager_id self-FK NULL for CEO, hire_date, salary) Data quirks to reason about: customers 19 & 20 never ordered; product 15 never sold; orders 5 & 23 are CANCELLED with no payment row; some orders have a FAILED payment followed by a SUCCESS; RETURNED orders also carry a REFUNDED payment, so filtering payments on status matters. Question #1 (1. SELECT basics, Easy): List every product with its name, category and price, most expensive first. Expected result shape: 15 rows sorted by price. My SQL: ```sql <PASTE YOUR SQL HERE> ``` Task: 1. Say if my query answers the question correctly (check joins, filters, grouping). 2. TEACH the logical execution order for THIS query — FROM, JOIN (show what the joined rows look like), WHERE, GROUP BY (what each group contains), HAVING (which groups survive), SELECT, ORDER BY — with a tiny worked example of the intermediate result at each stage. 3. Point out exactly where my mental model went wrong if it did. 4. Only then show the corrected/idiomatic query. 5. Give me ONE rule of thumb to remember for next time. Be direct — name real mistakes plainly. Do not pad with praise.

Sheet 🔑 Solutions
A1: Reference Solutions (MySQL 8) — every query validated against the database. Try first!
A2: # | B2: Question | C2: Reference SQL | D2: Why it works
A3: 1 | B3: List every product with its name, category and price, most expensive first. | C3: SELECT name, category, price FROM products ORDER BY price DESC; | D3: ORDER BY price DESC; select only the 3 columns you need.
A4: 2 | B4: Show the distinct cities customers live in, alphabetically. | C4: SELECT DISTINCT city FROM customers ORDER BY city; | D4: DISTINCT removes repeats.
A5: 3 | B5: Show the name and city of every Enterprise-segment customer. | C5: SELECT name, city FROM customers WHERE segment = 'Enterprise'; | D5: WHERE segment = 'Enterprise'.
A6: 4 | B6: Find the 5 most expensive products (name, price). | C6: SELECT name, price FROM products ORDER BY price DESC LIMIT 5; | D6: ORDER BY price DESC then LIMIT 5.
A7: 5 | B7: List products priced between 1000 and 5000, cheapest first. | C7: SELECT name, price FROM products WHERE price BETWEEN 1000 AND 5000 ORDER BY price; | D7: BETWEEN is inclusive on both ends.
A8: 6 | B8: For Electronics, show name and a 20%-off price as discounted_price. | C8: SELECT name, ROUND(price*0.8,2) AS discounted_price FROM products WHERE category='Electronics'; | D8: Compute price*0.8 and alias it with AS.
A9: 7 | B9: Customers who signed up during 2023 (name, signup_date). | C9: SELECT name, signup_date FROM customers WHERE signup_date BETWEEN '2023-01-01' AND '2023-12-31'; | D9: BETWEEN '2023-01-01' AND '2023-12-31' (or YEAR(signup_date)=2023).
A10: 8 | B10: Orders that were CANCELLED or RETURNED. | C10: SELECT order_id, status FROM orders WHERE status IN ('CANCELLED','RETURNED'); | D10: status IN ('CANCELLED','RETURNED').
A11: 9 | B11: Customers whose name starts with the letter A. | C11: SELECT name FROM customers WHERE name LIKE 'A%'; | D11: LIKE 'A%' — % is the wildcard.
A12: 10 | B12: Products that have no cost recorded. | C12: SELECT name, category FROM products WHERE cost IS NULL; | D12: NULL is tested with IS NULL, never with = NULL.
A13: 11 | B13: WEB-channel orders placed in Q1 2024. | C13: SELECT order_id, order_date FROM orders WHERE channel='WEB' AND order_date BETWEEN '2024-01-01' AND '2024-03-31'; | D13: Combine channel='WEB' AND a date range.
A14: 12 | B14: All payments that did not succeed. | C14: SELECT payment_id, order_id, amount, status FROM payments WHERE status <> 'SUCCESS'; | D14: status <> 'SUCCESS' (or NOT IN).
... A56: 54 | B56: New customers acquired per signup month (signup_month, new_customers). | C56: SELECT DATE_FORMAT(signup_date,'%Y-%m') AS signup_month, COUNT(*) AS new_customers FROM customers GROUP BY signup_month ORDER BY signup_month; | D56: DATE_FORMAT(signup_date,'%Y-%m'); COUNT; GROUP BY.

Sheet ⚙ data
A1: # | B1: topic | C1: diff | D1: question | E1: hint_expected
A2: 1 | B2: 1. SELECT basics | C2: Easy | D2: List every product with its name, category and price, most expensive first. | E2: 15 rows sorted by price.
A3: 2 | B3: 1. SELECT basics | C3: Easy | D3: Show the distinct cities customers live in, alphabetically. | E3: 9 unique cities.
A4: 3 | B4: 1. SELECT basics | C4: Easy | D4: Show the name and city of every Enterprise-segment customer. | E4: Subset of customers.
A5: 4 | B5: 1. SELECT basics | C5: Easy | D5: Find the 5 most expensive products (name, price). | E5: 5 rows.
A6: 5 | B6: 1. SELECT basics | C6: Medium | D6: List products priced between 1000 and 5000, cheapest first. | E6: Mid-range products.
A7: 6 | B7: 1. SELECT basics | C7: Medium | D7: For Electronics, show name and a 20%-off price as discounted_price. | E7: 4 electronics rows.
A8: 7 | B8: 2. Filtering | C8: Easy | D8: Customers who signed up during 2023 (name, signup_date). | E8: 2023 signups.
A9: 8 | B9: 2. Filtering | C9: Easy | D9: Orders that were CANCELLED or RETURNED. | E9: 4 rows.
A10: 9 | B10: 2. Filtering | C10: Easy | D10: Customers whose name starts with the letter A. | E10: Aarav.
A11: 10 | B11: 2. Filtering | C11: Medium | D11: Products that have no cost recorded. | E11: 1 row (Cloud IDE License).
A12: 11 | B12: 2. Filtering | C12: Medium | D12: WEB-channel orders placed in Q1 2024. | E12: A few orders.
A13: 12 | B13: 2. Filtering | C13: Medium | D13: All payments that did not succeed. | E13: FAILED + REFUNDED rows.
... A55: 54 | B55: 9. Dates & advanced | C55: Hard | D55: New customers acquired per signup month (signup_month, new_customers). | E55: Acquisition curve.
